langchain_vdms/__init__.py
langchain_vdms/py.typed
langchain_vdms/utils.py
langchain_vdms/vectorstores.py
langchain_vdms-0.2.0.dist-info/METADATA
langchain_vdms-0.2.0.dist-info/WHEEL
langchain_vdms-0.2.0.dist-info/licenses/LICENSE
langchain_vdms-0.2.0.dist-info/RECORD
