Metadata-Version: 2.4
Name: langchain-vdms
Version: 0.2.0
Summary: An integration package connecting VDMS and LangChain
License: MIT
License-File: LICENSE
Requires-Python: >=3.10,<4.0
Classifier: License :: OSI Approved :: MIT License
Classifier: Programming Language :: Python :: 3
Classifier: Programming Language :: Python :: 3.10
Classifier: Programming Language :: Python :: 3.11
Classifier: Programming Language :: Python :: 3.12
Classifier: Programming Language :: Python :: 3.13
Classifier: Programming Language :: Python :: 3.14
Requires-Dist: langchain-core (>=1.0.0,<2.0.0)
Requires-Dist: vdms (>=0.0.22)
Project-URL: Repository, https://github.com/IntelLabs/langchain-vdms
Project-URL: Release Notes, https://github.com/IntelLabs/langchain-vdms/releases
Project-URL: Source Code, https://github.com/IntelLabs/langchain-vdms
